openapi_client/__init__.py
openapi_client/api_client.py
openapi_client/configuration.py
openapi_client/exceptions.py
openapi_client/rest.py
openapi_client/api/__init__.py
openapi_client/api/default_api.py
openapi_client/api/pzi_sdk.py
openapi_client/api/setup.py
openapi_client/models/__init__.py
openapi_client/models/error_message.py
openapi_client/models/factor.py
openapi_client/models/factor_type.py
openapi_client/models/identity.py
openapi_client/models/inline_response201.py
openapi_client/models/post_identity_body.py
proofzeroclient/__init__.py
proofzeroclient/api_client.py
proofzeroclient/configuration.py
proofzeroclient/exceptions.py
proofzeroclient/rest.py
proofzeroclient/api/__init__.py
proofzeroclient/api/default_api.py
proofzeroclient/api/pzi_sdk.py
proofzeroclient/api/setup.py
proofzeroclient/models/__init__.py
proofzeroclient/models/error_message.py
proofzeroclient/models/factor.py
proofzeroclient/models/factor_type.py
proofzeroclient/models/identity.py
proofzeroclient/models/inline_response201.py
proofzeroclient/models/post_identity_body.py
proofzeroclient-0.0.2.dist-info/METADATA
proofzeroclient-0.0.2.dist-info/WHEEL
proofzeroclient-0.0.2.dist-info/top_level.txt
proofzeroclient-0.0.2.dist-info/RECORD
